project_runpy/__init__.py
project_runpy/heidi.py
project_runpy/tim.py
project_runpy-1.1.2.dist-info/LICENSE
project_runpy-1.1.2.dist-info/WHEEL
project_runpy-1.1.2.dist-info/METADATA
project_runpy-1.1.2.dist-info/RECORD
