Metadata-Version: 2.1
Name: project_runpy
Version: 1.1.2
Summary: Helper utilities for Python projects
Home-page: https://github.com/crccheck/project_runpy
Author: Chris Chang
Author-email: c@crccheck.com
Requires-Python: >=3
Classifier: Development Status :: 4 - Beta
Classifier: Intended Audience :: Developers
Classifier: License :: OSI Approved :: Apache Software License
Classifier: Operating System :: OS Independent
Classifier: Programming Language :: Python :: 3.7
Classifier: Programming Language :: Python :: 3.8
Classifier: Programming Language :: Python :: 3.9
Classifier: Programming Language :: Python :: 3.10
Classifier: Programming Language :: Python :: 3.11
Classifier: Topic :: Software Development :: Libraries :: Python Modules
